{
 "data": "2026-06-21",
 "jogos_disputados": 38,
 "posicoes": {
  "Daniel Boa Nova": 1,
  "Alexandre Capucho (Açaí)": 2,
  "Alessandro Berê": 3,
  "Carolina Capucho": 4,
  "Marcelo Cabral": 5,
  "Christian": 6,
  "Garibes": 7,
  "Pedro Augusto": 8,
  "Felipe Rocha": 9,
  "Thiago Ribeiro": 10,
  "Fernando Rocha": 11,
  "Felipe de Paula": 12,
  "Tiago Varalli": 13,
  "Fernanda Mora": 14,
  "Marcia Azenha": 15,
  "Cauê Rademaker": 16,
  "Denis": 17,
  "Gabriel Barretti": 18,
  "Fernando Lacerta": 19,
  "Fábio Rocha": 20,
  "Marcelo Frade": 21,
  "Bernardo Rocha": 22,
  "Luma": 23,
  "Oscar": 24,
  "Rafael Serbaro": 25,
  "Rubem de Paula": 26,
  "Camila Anticaglia": 27,
  "Sérgio Cruz": 28,
  "Leonardo Siqueira": 29,
  "Rui de Oliveira Filho": 30,
  "Vladimir": 31,
  "Cristiano Mendonça": 32,
  "Gui Caram": 33,
  "Heloisa Mora": 34,
  "Rogério da Veiga": 35,
  "Guilherme Assis": 36,
  "Caca e Bibi": 37,
  "Guto": 38,
  "Leo Soares": 39,
  "Renato Izar": 40,
  "Tiago Gavião": 41,
  "Carbonell": 42,
  "Duda Coimbra": 43,
  "Heitor Aroeira": 44,
  "Sylvia Mora": 45,
  "Alexandre Moretti": 46,
  "César de Oliveira Frade": 47,
  "Beatriz Latorre": 48,
  "Paulo Victor": 49,
  "Bernardo Ganso": 50,
  "Didi Adriano": 51,
  "Tanabe": 52,
  "Daso M Coimbra": 53,
  "Ricardo Rocha": 54,
  "Thiago Cinelli": 55,
  "Moisés": 56,
  "Bruno Varalli": 57,
  "Herbert Quirino": 58,
  "Mirena": 59,
  "Henrique Nunes": 60,
  "Octavio": 61,
  "Estevão Scripilliti": 62,
  "Janine Mello": 63,
  "Tato (Renato Flit)": 64,
  "Almir Teubl Sanches": 65,
  "Henrique Frizzo": 66,
  "Jaercio Ferreira da Silva": 67,
  "Thiago Pedroso": 68,
  "Igor Zibordi": 69,
  "Everton Trindade": 70,
  "Glemar Coelho": 71,
  "Guilherme Ramalho": 72,
  "Roberto Braga": 73,
  "Cora": 74,
  "Gustavo Coimbra": 75,
  "Pedro Chueiri": 76,
  "Torrão": 77,
  "Lucas Frizzo": 78,
  "Felipe Ramalho": 79,
  "Marcelo Conduru": 80,
  "Bernardo Paglia": 81,
  "Diângeli Soares Camargo": 82,
  "Sandro Eli": 83,
  "PROBER": 84,
  "Vanessa Soares Camargo": 85,
  "Jorge Ramalho": 86,
  "Helvio Mendes": 87,
  "Marcel Belfiore": 88,
  "Silvio Godoy": 89
 },
 "total_participantes": 89
}